dwebsocket/__init__.py
dwebsocket/decorators.py
dwebsocket/factory.py
dwebsocket/middleware.py
dwebsocket/websocket.py
dwebsocket/backends/__init__.py
dwebsocket/backends/default/__init__.py
dwebsocket/backends/default/factory.py
dwebsocket/backends/default/protocols.py
dwebsocket/backends/default/websocket.py
dwebsocket/backends/uwsgi/__init__.py
dwebsocket/backends/uwsgi/factory.py
dwebsocket2-0.0.3.dist-info/LICENSE
dwebsocket2-0.0.3.dist-info/METADATA
dwebsocket2-0.0.3.dist-info/WHEEL
dwebsocket2-0.0.3.dist-info/top_level.txt
dwebsocket2-0.0.3.dist-info/zip-safe
dwebsocket2-0.0.3.dist-info/RECORD
