Metadata-Version: 2.1
Name: dwebsocket2
Version: 0.0.3
Summary: 借鉴原作者做调整
Home-page: http://github.com/duanhongyi/dwebsocket
Author: zack
Author-email: 1125564921@qq.com
License: BSD
Classifier: Development Status :: 5 - Production/Stable
Classifier: Environment :: Web Environment
Classifier: Framework :: Django
Classifier: Intended Audience :: Developers
Classifier: License :: OSI Approved :: BSD License
Classifier: Operating System :: OS Independent
Classifier: Programming Language :: Python
Classifier: Topic :: Software Development :: Libraries :: Python Modules
Classifier: Topic :: Utilities
License-File: LICENSE
Requires-Dist: setuptools
Requires-Dist: six
